check.py
brew_compat-0.1.0.dist-info/LICENSE
brew_compat-0.1.0.dist-info/METADATA
brew_compat-0.1.0.dist-info/WHEEL
brew_compat-0.1.0.dist-info/entry_points.txt
brew_compat-0.1.0.dist-info/top_level.txt
brew_compat-0.1.0.dist-info/RECORD
