Metadata-Version: 2.1
Name: brew-compat
Version: 0.1.0
Summary: CLI tool for checking homebrew formulae compatibility for different macOS versions
Home-page: https://github.com/manojkarthick/brew-compat
Author: Manoj Karthick
Author-email: manojkarthick@ymail.com
License: MIT License
Keywords: homebrew,brew,cli
Platform: UNKNOWN
Classifier: Development Status :: 4 - Beta
Classifier: Intended Audience :: Developers
Classifier: License :: OSI Approved :: MIT License
Classifier: Operating System :: OS Independent
Requires-Python: >=3.6
Requires-Dist: requests
Requires-Dist: prettytable
